{
  "id": 153,
  "title": "Table 21",
  "content": "| Life, AD&D and supplemental benefits |  |\n| --- | --- |\n| Life Insurance, AD&D, and Group Accident | Group Critical Illness, Group Hospital Indemnity |\n| MetLife | www.metlife.com/info/companya 1.833.891.5433 (for policy questions, inquiries and claims) . Life and AD&D Claims: Press 1 |\n|  | · Statement of Health or Evidence of Insurability: Press 2 . Critical Illness, Hospital Indemnity or Accident Insurance: Press 3 |\n",
  "page": 49,
  "source": "Company_A_2025_Health&Well-Being_Guide.pdf"
}